pyarchops_dnsmasq/__init__.py
pyarchops_dnsmasq/dnsmasq.py
pyarchops_dnsmasq-0.0.2.dist-info/AUTHORS.rst
pyarchops_dnsmasq-0.0.2.dist-info/LICENSE
pyarchops_dnsmasq-0.0.2.dist-info/METADATA
pyarchops_dnsmasq-0.0.2.dist-info/WHEEL
pyarchops_dnsmasq-0.0.2.dist-info/top_level.txt
pyarchops_dnsmasq-0.0.2.dist-info/RECORD
