Metadata-Version: 2.1
Name: pyarchops-dnsmasq
Version: 0.0.2
Summary: Install All dnsmasq
Home-page: https://github.com/pyarchops/dnsmasq
Author: Azul
Author-email: pyarchops@azulinho.com
License: MIT license
Keywords: pyarchops_dnsmasq
Platform: UNKNOWN
Classifier: Development Status :: 2 - Pre-Alpha
Classifier: Intended Audience :: Developers
Classifier: License :: OSI Approved :: MIT License
Classifier: Natural Language :: English
Classifier: Programming Language :: Python :: 3.7
Requires-Dist: suitable
